HISTORY.rst
LICENSE
MANIFEST.in
README.rst
setup.py
revise/__init__.py
revise/core.py
revise/errors.py
revise/model.py
revise/types.py
revise/utils.py
revise.egg-info/PKG-INFO
revise.egg-info/SOURCES.txt
revise.egg-info/dependency_links.txt
revise.egg-info/not-zip-safe
revise.egg-info/requires.txt
revise.egg-info/top_level.txt