Metadata-Version: 1.1
Name: revise
Version: 0.0.3
Summary: Simple Schemas for Flask JSON Validation
Home-page: http://github.com/rhyselsmore/revise
Author: Rhys Elsmore
Author-email: me@rhys.io
License: Copyright 2013 Rhys Elsmore
